vulidentify/__init__.py
vulidentify/django.py
vulidentify/functions.py
vulidentify-0.1.0.dist-info/METADATA
vulidentify-0.1.0.dist-info/WHEEL
vulidentify-0.1.0.dist-info/top_level.txt
vulidentify-0.1.0.dist-info/RECORD
