Metadata-Version: 2.1
Name: vulidentify
Version: 0.1.0
Summary: le epic vulnerability identify for my hecking django!
Home-page: UNKNOWN
Author: harrycritchley
Author-email: UNKNOWN
License: UNKNOWN
Platform: UNKNOWN
Classifier: Development Status :: 3 - Alpha
Classifier: Topic :: Utilities
Classifier: License :: OSI Approved :: BSD License
